heng/__init__.py
heng/test.py
heng-0.1.0.dist-info/METADATA
heng-0.1.0.dist-info/WHEEL
heng-0.1.0.dist-info/top_level.txt
heng-0.1.0.dist-info/RECORD
